{
  "formatVersion": 1,
  "database": {
    "version": 1,
    "identityHash": "498614732f06284834cf3f0c79035f13",
    "entities": [
      {
        "tableName": "plants",
        "createSql": "CREATE TABLE IF NOT EXISTS `${TABLE_NAME}` (`id` INTEGER PRIMARY KEY AUTOINCREMENT NOT NULL, `name` TEXT NOT NULL, `description` TEXT NOT NULL, `isIndoor` INTEGER NOT NULL, `species` TEXT NOT NULL, `plantedOn` INTEGER NOT NULL, `createdOn` INTEGER NOT NULL, `wateringInterval` TEXT NOT NULL DEFAULT 'MONTHLY', `apiId` INTEGER, `sensorAddress` TEXT)",
        "fields": [
          {
            "fieldPath": "id",
            "columnName": "id",
            "affinity": "INTEGER",
            "notNull": true
          },
          {
            "fieldPath": "name",
            "columnName": "name",
            "affinity": "TEXT",
            "notNull": true
          },
          {
            "fieldPath": "description",
            "columnName": "description",
            "affinity": "TEXT",
            "notNull": true
          },
          {
            "fieldPath": "isIndoor",
            "columnName": "isIndoor",
            "affinity": "INTEGER",
            "notNull": true
          },
          {
            "fieldPath": "species",
            "columnName": "species",
            "affinity": "TEXT",
            "notNull": true
          },
          {
            "fieldPath": "plantedOn",
            "columnName": "plantedOn",
            "affinity": "INTEGER",
            "notNull": true
          },
          {
            "fieldPath": "createdOn",
            "columnName": "createdOn",
            "affinity": "INTEGER",
            "notNull": true
          },
          {
            "fieldPath": "wateringInterval",
            "columnName": "wateringInterval",
            "affinity": "TEXT",
            "notNull": true,
            "defaultValue": "'MONTHLY'"
          },
          {
            "fieldPath": "apiId",
            "columnName": "apiId",
            "affinity": "INTEGER"
          },
          {
            "fieldPath": "sensorAddress",
            "columnName": "sensorAddress",
            "affinity": "TEXT"
          }
        ],
        "primaryKey": {
          "autoGenerate": true,
          "columnNames": [
            "id"
          ]
        }
      },
      {
        "tableName": "notes",
        "createSql": "CREATE TABLE IF NOT EXISTS `${TABLE_NAME}` (`id` INTEGER PRIMARY KEY AUTOINCREMENT NOT NULL, `plant` INTEGER NOT NULL, `title` TEXT NOT NULL, `note` TEXT NOT NULL, FOREIGN KEY(`plant`) REFERENCES `plants`(`id`) ON UPDATE NO ACTION ON DELETE CASCADE )",
        "fields": [
          {
            "fieldPath": "id",
            "columnName": "id",
            "affinity": "INTEGER",
            "notNull": true
          },
          {
            "fieldPath": "plant",
            "columnName": "plant",
            "affinity": "INTEGER",
            "notNull": true
          },
          {
            "fieldPath": "title",
            "columnName": "title",
            "affinity": "TEXT",
            "notNull": true
          },
          {
            "fieldPath": "note",
            "columnName": "note",
            "affinity": "TEXT",
            "notNull": true
          }
        ],
        "primaryKey": {
          "autoGenerate": true,
          "columnNames": [
            "id"
          ]
        },
        "foreignKeys": [
          {
            "table": "plants",
            "onDelete": "CASCADE",
            "onUpdate": "NO ACTION",
            "columns": [
              "plant"
            ],
            "referencedColumns": [
              "id"
            ]
          }
        ]
      },
      {
        "tableName": "wateringHistory",
        "createSql": "CREATE TABLE IF NOT EXISTS `${TABLE_NAME}` (`plant` INTEGER NOT NULL, `date` INTEGER NOT NULL, PRIMARY KEY(`plant`, `date`), FOREIGN KEY(`plant`) REFERENCES `plants`(`id`) ON UPDATE NO ACTION ON DELETE CASCADE )",
        "fields": [
          {
            "fieldPath": "plant",
            "columnName": "plant",
            "affinity": "INTEGER",
            "notNull": true
          },
          {
            "fieldPath": "date",
            "columnName": "date",
            "affinity": "INTEGER",
            "notNull": true
          }
        ],
        "primaryKey": {
          "autoGenerate": false,
          "columnNames": [
            "plant",
            "date"
          ]
        },
        "indices": [
          {
            "name": "index_wateringHistory_plant",
            "unique": false,
            "columnNames": [
              "plant"
            ],
            "orders": [],
            "createSql": "CREATE INDEX IF NOT EXISTS `index_wateringHistory_plant` ON `${TABLE_NAME}` (`plant`)"
          }
        ],
        "foreignKeys": [
          {
            "table": "plants",
            "onDelete": "CASCADE",
            "onUpdate": "NO ACTION",
            "columns": [
              "plant"
            ],
            "referencedColumns": [
              "id"
            ]
          }
        ]
      },
      {
        "tableName": "wateringSchedule",
        "createSql": "CREATE TABLE IF NOT EXISTS `${TABLE_NAME}` (`plant` INTEGER NOT NULL, `day` TEXT NOT NULL, `startingDate` INTEGER NOT NULL, PRIMARY KEY(`plant`, `day`), FOREIGN KEY(`plant`) REFERENCES `plants`(`id`) ON UPDATE NO ACTION ON DELETE CASCADE )",
        "fields": [
          {
            "fieldPath": "plant",
            "columnName": "plant",
            "affinity": "INTEGER",
            "notNull": true
          },
          {
            "fieldPath": "day",
            "columnName": "day",
            "affinity": "TEXT",
            "notNull": true
          },
          {
            "fieldPath": "startingDate",
            "columnName": "startingDate",
            "affinity": "INTEGER",
            "notNull": true
          }
        ],
        "primaryKey": {
          "autoGenerate": false,
          "columnNames": [
            "plant",
            "day"
          ]
        },
        "foreignKeys": [
          {
            "table": "plants",
            "onDelete": "CASCADE",
            "onUpdate": "NO ACTION",
            "columns": [
              "plant"
            ],
            "referencedColumns": [
              "id"
            ]
          }
        ]
      },
      {
        "tableName": "plantDetails",
        "createSql": "CREATE TABLE IF NOT EXISTS `${TABLE_NAME}` (`id` INTEGER NOT NULL, `updatedOn` INTEGER NOT NULL, `commonName` TEXT NOT NULL, `scientificName` TEXT NOT NULL, `wateringValue` TEXT NOT NULL, `wateringUnit` TEXT NOT NULL, `sunlight` TEXT NOT NULL, `pruningMonths` TEXT NOT NULL, `soil` TEXT NOT NULL, `description` TEXT NOT NULL, PRIMARY KEY(`id`), FOREIGN KEY(`id`) REFERENCES `plants`(`id`) ON UPDATE NO ACTION ON DELETE CASCADE )",
        "fields": [
          {
            "fieldPath": "id",
            "columnName": "id",
            "affinity": "INTEGER",
            "notNull": true
          },
          {
            "fieldPath": "updatedOn",
            "columnName": "updatedOn",
            "affinity": "INTEGER",
            "notNull": true
          },
          {
            "fieldPath": "commonName",
            "columnName": "commonName",
            "affinity": "TEXT",
            "notNull": true
          },
          {
            "fieldPath": "scientificName",
            "columnName": "scientificName",
            "affinity": "TEXT",
            "notNull": true
          },
          {
            "fieldPath": "wateringValue",
            "columnName": "wateringValue",
            "affinity": "TEXT",
            "notNull": true
          },
          {
            "fieldPath": "wateringUnit",
            "columnName": "wateringUnit",
            "affinity": "TEXT",
            "notNull": true
          },
          {
            "fieldPath": "sunlight",
            "columnName": "sunlight",
            "affinity": "TEXT",
            "notNull": true
          },
          {
            "fieldPath": "pruningMonths",
            "columnName": "pruningMonths",
            "affinity": "TEXT",
            "notNull": true
          },
          {
            "fieldPath": "soil",
            "columnName": "soil",
            "affinity": "TEXT",
            "notNull": true
          },
          {
            "fieldPath": "description",
            "columnName": "description",
            "affinity": "TEXT",
            "notNull": true
          }
        ],
        "primaryKey": {
          "autoGenerate": false,
          "columnNames": [
            "id"
          ]
        },
        "foreignKeys": [
          {
            "table": "plants",
            "onDelete": "CASCADE",
            "onUpdate": "NO ACTION",
            "columns": [
              "id"
            ],
            "referencedColumns": [
              "id"
            ]
          }
        ]
      },
      {
        "tableName": "plantMedia",
        "createSql": "CREATE TABLE IF NOT EXISTS `${TABLE_NAME}` (`plant` INTEGER NOT NULL, `media` TEXT NOT NULL, PRIMARY KEY(`plant`, `media`), FOREIGN KEY(`plant`) REFERENCES `plants`(`id`) ON UPDATE NO ACTION ON DELETE CASCADE )",
        "fields": [
          {
            "fieldPath": "plant",
            "columnName": "plant",
            "affinity": "INTEGER",
            "notNull": true
          },
          {
            "fieldPath": "media",
            "columnName": "media",
            "affinity": "TEXT",
            "notNull": true
          }
        ],
        "primaryKey": {
          "autoGenerate": false,
          "columnNames": [
            "plant",
            "media"
          ]
        },
        "foreignKeys": [
          {
            "table": "plants",
            "onDelete": "CASCADE",
            "onUpdate": "NO ACTION",
            "columns": [
              "plant"
            ],
            "referencedColumns": [
              "id"
            ]
          }
        ]
      },
      {
        "tableName": "weatherRecord",
        "createSql": "CREATE TABLE IF NOT EXISTS `${TABLE_NAME}` (`timestamp` INTEGER NOT NULL, `hasRained` INTEGER NOT NULL, `rainVolume` REAL, PRIMARY KEY(`timestamp`))",
        "fields": [
          {
            "fieldPath": "timestamp",
            "columnName": "timestamp",
            "affinity": "INTEGER",
            "notNull": true
          },
          {
            "fieldPath": "hasRained",
            "columnName": "hasRained",
            "affinity": "INTEGER",
            "notNull": true
          },
          {
            "fieldPath": "rainVolume",
            "columnName": "rainVolume",
            "affinity": "REAL"
          }
        ],
        "primaryKey": {
          "autoGenerate": false,
          "columnNames": [
            "timestamp"
          ]
        }
      },
      {
        "tableName": "userDailyRecord",
        "createSql": "CREATE TABLE IF NOT EXISTS `${TABLE_NAME}` (`date` INTEGER NOT NULL, `streakMaintained` INTEGER NOT NULL, PRIMARY KEY(`date`))",
        "fields": [
          {
            "fieldPath": "date",
            "columnName": "date",
            "affinity": "INTEGER",
            "notNull": true
          },
          {
            "fieldPath": "streakMaintained",
            "columnName": "streakMaintained",
            "affinity": "INTEGER",
            "notNull": true
          }
        ],
        "primaryKey": {
          "autoGenerate": false,
          "columnNames": [
            "date"
          ]
        }
      }
    ],
    "setupQueries": [
      "CREATE TABLE IF NOT EXISTS room_master_table (id INTEGER PRIMARY KEY,identity_hash TEXT)",
      "INSERT OR REPLACE INTO room_master_table (id,identity_hash) VALUES(42, '498614732f06284834cf3f0c79035f13')"
    ]
  }
}